gitink/__init__.py
gitink/cli.py
gitink/color.py
gitink/main.py
gitink/svg.py
gitink/test.py
gitink/test/down.svg
gitink/test/down.txt
gitink/test/right.svg
gitink/test/right.txt
gitink/test/up.svg
gitink/test/up.txt
gitink-0.2.2.dist-info/entry_points.txt
gitink-0.2.2.dist-info/LICENSE
gitink-0.2.2.dist-info/WHEEL
gitink-0.2.2.dist-info/METADATA
gitink-0.2.2.dist-info/RECORD
