Metadata-Version: 2.1
Name: gitink
Version: 0.2.2
Summary: gitink: ASCII to SVG Git log graph visualizer.
Author-email: Radovan Bast <radovan.bast@uit.no>
Classifier: License :: OSI Approved :: Mozilla Public License 2.0 (MPL 2.0)
Requires-Dist: click
Requires-Dist: ascii2graph
Project-URL: Home, https://github.com/bast/gitink
